LICENSE
MANIFEST.in
README.md
setup.cfg
setup.py
src/reprb/__init__.py
src/reprb/reprb.py
src/reprb.egg-info/PKG-INFO
src/reprb.egg-info/SOURCES.txt
src/reprb.egg-info/dependency_links.txt
src/reprb.egg-info/top_level.txt
src/reprb/c_extension/_reprb.c