Metadata-Version: 2.1
Name: reprb
Version: 1.0.6
Summary: Represent bytes with printable characters
Home-page: https://github.com/testzero-wz/reprb
Author: T3stzer0
Author-email: testzero.wz@gmail.com
Classifier: Programming Language :: Python :: 3
Classifier: License :: OSI Approved :: MIT License
Classifier: Operating System :: OS Independent
Requires-Python: >=3
License-File: LICENSE
